[
  {
    "rank": 1,
    "title": "猴子虐猫",
    "hot": 2057854,
    "tag": "新",
    "link": "https://s.weibo.com/weibo?q=%E7%8C%B4%E5%AD%90%E8%99%90%E7%8C%AB&t=31&band_rank=1&Refer=top"
  },
  {
    "rank": 2,
    "title": "交警通报虞书欣司机高速倒车",
    "hot": 1476424,
    "tag": "新",
    "link": "https://s.weibo.com/weibo?q=%23%E4%BA%A4%E8%AD%A6%E9%80%9A%E6%8A%A5%E8%99%9E%E4%B9%A6%E6%AC%A3%E5%8F%B8%E6%9C%BA%E9%AB%98%E9%80%9F%E5%80%92%E8%BD%A6%23&t=31&band_rank=2&Refer=top"
  },
  {
    "rank": 3,
    "title": "运20首飞成功11年",
    "hot": 1241291,
    "tag": "",
    "link": "https://s.weibo.com/weibo?q=%23%E8%BF%9020%E9%A6%96%E9%A3%9E%E6%88%90%E5%8A%9F11%E5%B9%B4%23&t=31&band_rank=3&Refer=top"
  },
  {
    "rank": 4,
    "title": "结婚为什么需要这么多被子",
    "hot": 1022147,
    "tag": "新",
    "link": "https://s.weibo.com/weibo?q=%23%E7%BB%93%E5%A9%9A%E4%B8%BA%E4%BB%80%E4%B9%88%E9%9C%80%E8%A6%81%E8%BF%99%E4%B9%88%E5%A4%9A%E8%A2%AB%E5%AD%90%23&t=31&band_rank=4&Refer=top"
  },
  {
    "rank": 5,
    "title": "2023媒体反感艺人TOP3",
    "hot": 918723,
    "tag": "新",
    "link": "https://s.weibo.com/weibo?q=%232023%E5%AA%92%E4%BD%93%E5%8F%8D%E6%84%9F%E8%89%BA%E4%BA%BATOP3%23&t=31&band_rank=5&Refer=top"
  },
  {
    "rank": 6,
    "title": "昆明动物园通报猴猫共处",
    "hot": 909592,
    "tag": "沸",
    "link": "https://s.weibo.com/weibo?q=%23%E6%98%86%E6%98%8E%E5%8A%A8%E7%89%A9%E5%9B%AD%E9%80%9A%E6%8A%A5%E7%8C%B4%E7%8C%AB%E5%85%B1%E5%A4%84%23&t=31&band_rank=6&Refer=top"
  },
  {
    "rank": 7,
    "title": "未定事件簿 古婚",
    "hot": 705557,
    "tag": "沸",
    "link": "https://s.weibo.com/weibo?q=%E6%9C%AA%E5%AE%9A%E4%BA%8B%E4%BB%B6%E7%B0%BF%20%E5%8F%A4%E5%A9%9A&t=31&band_rank=7&Refer=top"
  },
  {
    "rank": 8,
    "title": "于正回应",
    "hot": 666222,
    "tag": "新",
    "link": "https://s.weibo.com/weibo?q=%23%E4%BA%8E%E6%AD%A3%E5%9B%9E%E5%BA%94%23&t=31&band_rank=8&Refer=top"
  },
  {
    "rank": 9,
    "title": "谁家大学生房间里有三室一厅啊",
    "hot": 664988,
    "tag": "",
    "link": "https://s.weibo.com/weibo?q=%E8%B0%81%E5%AE%B6%E5%A4%A7%E5%AD%A6%E7%94%9F%E6%88%BF%E9%97%B4%E9%87%8C%E6%9C%89%E4%B8%89%E5%AE%A4%E4%B8%80%E5%8E%85%E5%95%8A&t=31&band_rank=9&Refer=top"
  },
  {
    "rank": 10,
    "title": "陈建斌回应网友二创甄嬛传",
    "hot": 639546,
    "tag": "新",
    "link": "https://s.weibo.com/weibo?q=%23%E9%99%88%E5%BB%BA%E6%96%8C%E5%9B%9E%E5%BA%94%E7%BD%91%E5%8F%8B%E4%BA%8C%E5%88%9B%E7%94%84%E5%AC%9B%E4%BC%A0%23&t=31&band_rank=10&Refer=top"
  },
  {
    "rank": 11,
    "title": "曝95生当着媒体在室内抽烟",
    "hot": 638445,
    "tag": "新",
    "link": "https://s.weibo.com/weibo?q=%23%E6%9B%9D95%E7%94%9F%E5%BD%93%E7%9D%80%E5%AA%92%E4%BD%93%E5%9C%A8%E5%AE%A4%E5%86%85%E6%8A%BD%E7%83%9F%23&t=31&band_rank=11&Refer=top"
  },
  {
    "rank": 12,
    "title": "金莎原以为观众会对孙丞潇很宽容",
    "hot": 563496,
    "tag": "新",
    "link": "https://s.weibo.com/weibo?q=%23%E9%87%91%E8%8E%8E%E5%8E%9F%E4%BB%A5%E4%B8%BA%E8%A7%82%E4%BC%97%E4%BC%9A%E5%AF%B9%E5%AD%99%E4%B8%9E%E6%BD%87%E5%BE%88%E5%AE%BD%E5%AE%B9%23&t=31&band_rank=12&Refer=top"
  },
  {
    "rank": 13,
    "title": "减重100斤的贾玲惊呆潘斌龙",
    "hot": 524188,
    "tag": "热",
    "link": "https://s.weibo.com/weibo?q=%23%E5%87%8F%E9%87%8D100%E6%96%A4%E7%9A%84%E8%B4%BE%E7%8E%B2%E6%83%8A%E5%91%86%E6%BD%98%E6%96%8C%E9%BE%99%23&t=31&band_rank=13&Refer=top"
  },
  {
    "rank": 14,
    "title": "11月大男婴哭湿口罩后闷死",
    "hot": 518996,
    "tag": "热",
    "link": "https://s.weibo.com/weibo?q=%2311%E6%9C%88%E5%A4%A7%E7%94%B7%E5%A9%B4%E5%93%AD%E6%B9%BF%E5%8F%A3%E7%BD%A9%E5%90%8E%E9%97%B7%E6%AD%BB%23&t=31&band_rank=14&Refer=top"
  },
  {
    "rank": 15,
    "title": "元梦龙年星动代言人宋雨琦",
    "hot": 513820,
    "tag": "",
    "link": "https://s.weibo.com/weibo?q=%23%E5%85%83%E6%A2%A6%E9%BE%99%E5%B9%B4%E6%98%9F%E5%8A%A8%E4%BB%A3%E8%A8%80%E4%BA%BA%E5%AE%8B%E9%9B%A8%E7%90%A6%23&t=31&band_rank=15&Refer=top"
  },
  {
    "rank": 16,
    "title": "大张伟 贾仙女让我做首健身时打气的歌",
    "hot": 509885,
    "tag": "",
    "link": "https://s.weibo.com/weibo?q=%E5%A4%A7%E5%BC%A0%E4%BC%9F%20%E8%B4%BE%E4%BB%99%E5%A5%B3%E8%AE%A9%E6%88%91%E5%81%9A%E9%A6%96%E5%81%A5%E8%BA%AB%E6%97%B6%E6%89%93%E6%B0%94%E7%9A%84%E6%AD%8C&t=31&band_rank=16&Refer=top"
  },
  {
    "rank": 17,
    "title": "徐娇怼于正",
    "hot": 456396,
    "tag": "",
    "link": "https://s.weibo.com/weibo?q=%E5%BE%90%E5%A8%87%E6%80%BC%E4%BA%8E%E6%AD%A3&t=31&band_rank=17&Refer=top"
  },
  {
    "rank": 18,
    "title": "世界之外 101变11",
    "hot": 409840,
    "tag": "",
    "link": "https://s.weibo.com/weibo?q=%E4%B8%96%E7%95%8C%E4%B9%8B%E5%A4%96%20101%E5%8F%9811&t=31&band_rank=18&Refer=top"
  },
  {
    "rank": 19,
    "title": "江西新余大火遇难者亲友发声",
    "hot": 388161,
    "tag": "新",
    "link": "https://s.weibo.com/weibo?q=%23%E6%B1%9F%E8%A5%BF%E6%96%B0%E4%BD%99%E5%A4%A7%E7%81%AB%E9%81%87%E9%9A%BE%E8%80%85%E4%BA%B2%E5%8F%8B%E5%8F%91%E5%A3%B0%23&t=31&band_rank=19&Refer=top"
  },
  {
    "rank": 20,
    "title": "王安宇发文告别花少",
    "hot": 319730,
    "tag": "",
    "link": "https://s.weibo.com/weibo?q=%E7%8E%8B%E5%AE%89%E5%AE%87%E5%8F%91%E6%96%87%E5%91%8A%E5%88%AB%E8%8A%B1%E5%B0%91&t=31&band_rank=20&Refer=top"
  },
  {
    "rank": 21,
    "title": "你认为嫁妆属于女方个人财产吗",
    "hot": 302850,
    "tag": "",
    "link": "https://s.weibo.com/weibo?q=%23%E4%BD%A0%E8%AE%A4%E4%B8%BA%E5%AB%81%E5%A6%86%E5%B1%9E%E4%BA%8E%E5%A5%B3%E6%96%B9%E4%B8%AA%E4%BA%BA%E8%B4%A2%E4%BA%A7%E5%90%97%23&t=31&band_rank=21&Refer=top"
  },
  {
    "rank": 22,
    "title": "爸爸20年储存60斤陈皮给女儿作嫁妆",
    "hot": 299568,
    "tag": "",
    "link": "https://s.weibo.com/weibo?q=%23%E7%88%B8%E7%88%B820%E5%B9%B4%E5%82%A8%E5%AD%9860%E6%96%A4%E9%99%88%E7%9A%AE%E7%BB%99%E5%A5%B3%E5%84%BF%E4%BD%9C%E5%AB%81%E5%A6%86%23&t=31&band_rank=22&Refer=top"
  },
  {
    "rank": 23,
    "title": "媒体评迪丽热巴可爱直率鲜活",
    "hot": 287400,
    "tag": "",
    "link": "https://s.weibo.com/weibo?q=%23%E5%AA%92%E4%BD%93%E8%AF%84%E8%BF%AA%E4%B8%BD%E7%83%AD%E5%B7%B4%E5%8F%AF%E7%88%B1%E7%9B%B4%E7%8E%87%E9%B2%9C%E6%B4%BB%23&t=31&band_rank=23&Refer=top"
  },
  {
    "rank": 24,
    "title": "落马女局长跑步机里藏价值666万黄金",
    "hot": 274868,
    "tag": "",
    "link": "https://s.weibo.com/weibo?q=%23%E8%90%BD%E9%A9%AC%E5%A5%B3%E5%B1%80%E9%95%BF%E8%B7%91%E6%AD%A5%E6%9C%BA%E9%87%8C%E8%97%8F%E4%BB%B7%E5%80%BC666%E4%B8%87%E9%BB%84%E9%87%91%23&t=31&band_rank=24&Refer=top"
  },
  {
    "rank": 25,
    "title": "女子遭研究生同学无视追讨礼金",
    "hot": 273589,
    "tag": "热",
    "link": "https://s.weibo.com/weibo?q=%23%E5%A5%B3%E5%AD%90%E9%81%AD%E7%A0%94%E7%A9%B6%E7%94%9F%E5%90%8C%E5%AD%A6%E6%97%A0%E8%A7%86%E8%BF%BD%E8%AE%A8%E7%A4%BC%E9%87%91%23&t=31&band_rank=25&Refer=top"
  },
  {
    "rank": 26,
    "title": "3元以下饮料仅剩10%",
    "hot": 261194,
    "tag": "",
    "link": "https://s.weibo.com/weibo?q=%233%E5%85%83%E4%BB%A5%E4%B8%8B%E9%A5%AE%E6%96%99%E4%BB%85%E5%89%A910%25%23&t=31&band_rank=26&Refer=top"
  },
  {
    "rank": 27,
    "title": "恋与深空首周流水超1.5亿",
    "hot": 260294,
    "tag": "新",
    "link": "https://s.weibo.com/weibo?q=%23%E6%81%8B%E4%B8%8E%E6%B7%B1%E7%A9%BA%E9%A6%96%E5%91%A8%E6%B5%81%E6%B0%B4%E8%B6%851.5%E4%BA%BF%23&t=31&band_rank=27&Refer=top"
  },
  {
    "rank": 28,
    "title": "世界之外正式公测",
    "hot": 241617,
    "tag": "",
    "link": "https://s.weibo.com/weibo?q=%23%E4%B8%96%E7%95%8C%E4%B9%8B%E5%A4%96%E6%AD%A3%E5%BC%8F%E5%85%AC%E6%B5%8B%23&t=31&band_rank=28&Refer=top"
  },
  {
    "rank": 29,
    "title": "俞敏洪称只依赖董宇辉不是正常公司",
    "hot": 240847,
    "tag": "新",
    "link": "https://s.weibo.com/weibo?q=%23%E4%BF%9E%E6%95%8F%E6%B4%AA%E7%A7%B0%E5%8F%AA%E4%BE%9D%E8%B5%96%E8%91%A3%E5%AE%87%E8%BE%89%E4%B8%8D%E6%98%AF%E6%AD%A3%E5%B8%B8%E5%85%AC%E5%8F%B8%23&t=31&band_rank=29&Refer=top"
  },
  {
    "rank": 30,
    "title": "德约科维奇被破发",
    "hot": 240548,
    "tag": "新",
    "link": "https://s.weibo.com/weibo?q=%E5%BE%B7%E7%BA%A6%E7%A7%91%E7%BB%B4%E5%A5%87%E8%A2%AB%E7%A0%B4%E5%8F%91&t=31&band_rank=30&Refer=top"
  },
  {
    "rank": 31,
    "title": "装扮了男朋友买的新车",
    "hot": 239034,
    "tag": "新",
    "link": "https://s.weibo.com/weibo?q=%E8%A3%85%E6%89%AE%E4%BA%86%E7%94%B7%E6%9C%8B%E5%8F%8B%E4%B9%B0%E7%9A%84%E6%96%B0%E8%BD%A6&t=31&band_rank=31&Refer=top"
  },
  {
    "rank": 32,
    "title": "辛芷蕾发了和花少团每个人的合照",
    "hot": 234916,
    "tag": "",
    "link": "https://s.weibo.com/weibo?q=%23%E8%BE%9B%E8%8A%B7%E8%95%BE%E5%8F%91%E4%BA%86%E5%92%8C%E8%8A%B1%E5%B0%91%E5%9B%A2%E6%AF%8F%E4%B8%AA%E4%BA%BA%E7%9A%84%E5%90%88%E7%85%A7%23&t=31&band_rank=32&Refer=top"
  },
  {
    "rank": 33,
    "title": "英雄联盟手游",
    "hot": 228164,
    "tag": "新",
    "link": "https://s.weibo.com/weibo?q=%E8%8B%B1%E9%9B%84%E8%81%94%E7%9B%9F%E6%89%8B%E6%B8%B8&t=31&band_rank=33&Refer=top"
  },
  {
    "rank": 34,
    "title": "王一博大秀彩排花絮",
    "hot": 205684,
    "tag": "新",
    "link": "https://s.weibo.com/weibo?q=%23%E7%8E%8B%E4%B8%80%E5%8D%9A%E5%A4%A7%E7%A7%80%E5%BD%A9%E6%8E%92%E8%8A%B1%E7%B5%AE%23&t=31&band_rank=34&Refer=top"
  },
  {
    "rank": 35,
    "title": "猫妈妈给喜爱的人类介绍它的小孩",
    "hot": 199889,
    "tag": "新",
    "link": "https://s.weibo.com/weibo?q=%E7%8C%AB%E5%A6%88%E5%A6%88%E7%BB%99%E5%96%9C%E7%88%B1%E7%9A%84%E4%BA%BA%E7%B1%BB%E4%BB%8B%E7%BB%8D%E5%AE%83%E7%9A%84%E5%B0%8F%E5%AD%A9&t=31&band_rank=35&Refer=top"
  },
  {
    "rank": 36,
    "title": "眠狼",
    "hot": 196701,
    "tag": "",
    "link": "https://s.weibo.com/weibo?q=%E7%9C%A0%E7%8B%BC&t=31&band_rank=36&Refer=top"
  },
  {
    "rank": 37,
    "title": "世界之外没有数值策划",
    "hot": 195876,
    "tag": "",
    "link": "https://s.weibo.com/weibo?q=%E4%B8%96%E7%95%8C%E4%B9%8B%E5%A4%96%E6%B2%A1%E6%9C%89%E6%95%B0%E5%80%BC%E7%AD%96%E5%88%92&t=31&band_rank=37&Refer=top"
  },
  {
    "rank": 38,
    "title": "市民热线回应动物园猴群与猫共处",
    "hot": 191852,
    "tag": "新",
    "link": "https://s.weibo.com/weibo?q=%23%E5%B8%82%E6%B0%91%E7%83%AD%E7%BA%BF%E5%9B%9E%E5%BA%94%E5%8A%A8%E7%89%A9%E5%9B%AD%E7%8C%B4%E7%BE%A4%E4%B8%8E%E7%8C%AB%E5%85%B1%E5%A4%84%23&t=31&band_rank=38&Refer=top"
  },
  {
    "rank": 39,
    "title": "澳网决赛",
    "hot": 183692,
    "tag": "新",
    "link": "https://s.weibo.com/weibo?q=%E6%BE%B3%E7%BD%91%E5%86%B3%E8%B5%9B&t=31&band_rank=39&Refer=top"
  },
  {
    "rank": 40,
    "title": "肖战GQ门牌号是生日",
    "hot": 180009,
    "tag": "新",
    "link": "https://s.weibo.com/weibo?q=%23%E8%82%96%E6%88%98GQ%E9%97%A8%E7%89%8C%E5%8F%B7%E6%98%AF%E7%94%9F%E6%97%A5%23&t=31&band_rank=40&Refer=top"
  },
  {
    "rank": 41,
    "title": "秦始皇帝陵1号陪葬墓取得重大考古收获",
    "hot": 169551,
    "tag": "新",
    "link": "https://s.weibo.com/weibo?q=%23%E7%A7%A6%E5%A7%8B%E7%9A%87%E5%B8%9D%E9%99%B51%E5%8F%B7%E9%99%AA%E8%91%AC%E5%A2%93%E5%8F%96%E5%BE%97%E9%87%8D%E5%A4%A7%E8%80%83%E5%8F%A4%E6%94%B6%E8%8E%B7%23&t=31&band_rank=41&Refer=top"
  },
  {
    "rank": 42,
    "title": "传音年终奖多发30%",
    "hot": 156627,
    "tag": "新",
    "link": "https://s.weibo.com/weibo?q=%23%E4%BC%A0%E9%9F%B3%E5%B9%B4%E7%BB%88%E5%A5%96%E5%A4%9A%E5%8F%9130%25%23&t=31&band_rank=42&Refer=top"
  },
  {
    "rank": 43,
    "title": "黄瀛子为杨紫新电影打call",
    "hot": 150186,
    "tag": "新",
    "link": "https://s.weibo.com/weibo?q=%23%E9%BB%84%E7%80%9B%E5%AD%90%E4%B8%BA%E6%9D%A8%E7%B4%AB%E6%96%B0%E7%94%B5%E5%BD%B1%E6%89%93call%23&t=31&band_rank=43&Refer=top"
  },
  {
    "rank": 44,
    "title": "不要再把肉泡水里解冻了",
    "hot": 148466,
    "tag": "",
    "link": "https://s.weibo.com/weibo?q=%23%E4%B8%8D%E8%A6%81%E5%86%8D%E6%8A%8A%E8%82%89%E6%B3%A1%E6%B0%B4%E9%87%8C%E8%A7%A3%E5%86%BB%E4%BA%86%23&t=31&band_rank=44&Refer=top"
  },
  {
    "rank": 45,
    "title": "肖战GQ封面预告",
    "hot": 147973,
    "tag": "",
    "link": "https://s.weibo.com/weibo?q=%23%E8%82%96%E6%88%98GQ%E5%B0%81%E9%9D%A2%E9%A2%84%E5%91%8A%23&t=31&band_rank=45&Refer=top"
  },
  {
    "rank": 46,
    "title": "少爷和我首支预告片",
    "hot": 147068,
    "tag": "新",
    "link": "https://s.weibo.com/weibo?q=%23%E5%B0%91%E7%88%B7%E5%92%8C%E6%88%91%E9%A6%96%E6%94%AF%E9%A2%84%E5%91%8A%E7%89%87%23&t=31&band_rank=46&Refer=top"
  },
  {
    "rank": 47,
    "title": "根管治疗或被一种化合物替代",
    "hot": 147003,
    "tag": "",
    "link": "https://s.weibo.com/weibo?q=%23%E6%A0%B9%E7%AE%A1%E6%B2%BB%E7%96%97%E6%88%96%E8%A2%AB%E4%B8%80%E7%A7%8D%E5%8C%96%E5%90%88%E7%89%A9%E6%9B%BF%E4%BB%A3%23&t=31&band_rank=47&Refer=top"
  },
  {
    "rank": 48,
    "title": "迪丽热巴告别花少",
    "hot": 142057,
    "tag": "",
    "link": "https://s.weibo.com/weibo?q=%23%E8%BF%AA%E4%B8%BD%E7%83%AD%E5%B7%B4%E5%91%8A%E5%88%AB%E8%8A%B1%E5%B0%91%23&t=31&band_rank=48&Refer=top"
  },
  {
    "rank": 49,
    "title": "专家称农村大量房子只造不住",
    "hot": 142034,
    "tag": "新",
    "link": "https://s.weibo.com/weibo?q=%23%E4%B8%93%E5%AE%B6%E7%A7%B0%E5%86%9C%E6%9D%91%E5%A4%A7%E9%87%8F%E6%88%BF%E5%AD%90%E5%8F%AA%E9%80%A0%E4%B8%8D%E4%BD%8F%23&t=31&band_rank=49&Refer=top"
  },
  {
    "rank": 50,
    "title": "猫说当初也没告诉我是合租啊",
    "hot": 141155,
    "tag": "新",
    "link": "https://s.weibo.com/weibo?q=%23%E7%8C%AB%E8%AF%B4%E5%BD%93%E5%88%9D%E4%B9%9F%E6%B2%A1%E5%91%8A%E8%AF%89%E6%88%91%E6%98%AF%E5%90%88%E7%A7%9F%E5%95%8A%23&t=31&band_rank=50&Refer=top"
  }
]
