[
  {
    "rank": 1,
    "title": "黄晓明 叶珂",
    "hot": 1759194,
    "tag": "热",
    "link": "https://s.weibo.com/weibo?q=%E9%BB%84%E6%99%93%E6%98%8E%20%E5%8F%B6%E7%8F%82&t=31&band_rank=1&Refer=top"
  },
  {
    "rank": 2,
    "title": "老人痛诉全身只有20元赌什么博",
    "hot": 1238562,
    "tag": "新",
    "link": "https://s.weibo.com/weibo?q=%23%E8%80%81%E4%BA%BA%E7%97%9B%E8%AF%89%E5%85%A8%E8%BA%AB%E5%8F%AA%E6%9C%8920%E5%85%83%E8%B5%8C%E4%BB%80%E4%B9%88%E5%8D%9A%23&t=31&band_rank=2&Refer=top"
  },
  {
    "rank": 3,
    "title": "青春华章",
    "hot": 1032078,
    "tag": "",
    "link": "https://s.weibo.com/weibo?q=%23%E9%9D%92%E6%98%A5%E5%8D%8E%E7%AB%A0%23&t=31&band_rank=3&Refer=top"
  },
  {
    "rank": 4,
    "title": "女生吃火锅遇可升降锅",
    "hot": 847921,
    "tag": "",
    "link": "https://s.weibo.com/weibo?q=%23%E5%A5%B3%E7%94%9F%E5%90%83%E7%81%AB%E9%94%85%E9%81%87%E5%8F%AF%E5%8D%87%E9%99%8D%E9%94%85%23&t=31&band_rank=4&Refer=top"
  },
  {
    "rank": 5,
    "title": "武艺爆料张碧晨喜欢在厕所吃饭",
    "hot": 808629,
    "tag": "热",
    "link": "https://s.weibo.com/weibo?q=%E6%AD%A6%E8%89%BA%E7%88%86%E6%96%99%E5%BC%A0%E7%A2%A7%E6%99%A8%E5%96%9C%E6%AC%A2%E5%9C%A8%E5%8E%95%E6%89%80%E5%90%83%E9%A5%AD&t=31&band_rank=5&Refer=top"
  },
  {
    "rank": 6,
    "title": "90后独生女独自面对父母离世",
    "hot": 502294,
    "tag": "",
    "link": "https://s.weibo.com/weibo?q=%2390%E5%90%8E%E7%8B%AC%E7%94%9F%E5%A5%B3%E7%8B%AC%E8%87%AA%E9%9D%A2%E5%AF%B9%E7%88%B6%E6%AF%8D%E7%A6%BB%E4%B8%96%23&t=31&band_rank=6&Refer=top"
  },
  {
    "rank": 7,
    "title": "黄轩女朋友",
    "hot": 493026,
    "tag": "热",
    "link": "https://s.weibo.com/weibo?q=%E9%BB%84%E8%BD%A9%E5%A5%B3%E6%9C%8B%E5%8F%8B&t=31&band_rank=7&Refer=top"
  },
  {
    "rank": 8,
    "title": "医院被曝一张CT片子套多个病历",
    "hot": 445194,
    "tag": "",
    "link": "https://s.weibo.com/weibo?q=%23%E5%8C%BB%E9%99%A2%E8%A2%AB%E6%9B%9D%E4%B8%80%E5%BC%A0CT%E7%89%87%E5%AD%90%E5%A5%97%E5%A4%9A%E4%B8%AA%E7%97%85%E5%8E%86%23&t=31&band_rank=8&Refer=top"
  },
  {
    "rank": 9,
    "title": "常说这4句话的人痴呆风险高",
    "hot": 418757,
    "tag": "",
    "link": "https://s.weibo.com/weibo?q=%23%E5%B8%B8%E8%AF%B4%E8%BF%994%E5%8F%A5%E8%AF%9D%E7%9A%84%E4%BA%BA%E7%97%B4%E5%91%86%E9%A3%8E%E9%99%A9%E9%AB%98%23&t=31&band_rank=9&Refer=top"
  },
  {
    "rank": 10,
    "title": "罚抄式处罚成为奶茶店管理惯例",
    "hot": 418640,
    "tag": "新",
    "link": "https://s.weibo.com/weibo?q=%23%E7%BD%9A%E6%8A%84%E5%BC%8F%E5%A4%84%E7%BD%9A%E6%88%90%E4%B8%BA%E5%A5%B6%E8%8C%B6%E5%BA%97%E7%AE%A1%E7%90%86%E6%83%AF%E4%BE%8B%23&t=31&band_rank=10&Refer=top"
  },
  {
    "rank": 11,
    "title": "赵丽颖在张碧晨家厕所睡过觉",
    "hot": 418638,
    "tag": "新",
    "link": "https://s.weibo.com/weibo?q=%E8%B5%B5%E4%B8%BD%E9%A2%96%E5%9C%A8%E5%BC%A0%E7%A2%A7%E6%99%A8%E5%AE%B6%E5%8E%95%E6%89%80%E7%9D%A1%E8%BF%87%E8%A7%89&t=31&band_rank=11&Refer=top"
  },
  {
    "rank": 12,
    "title": "半熟男女 假离婚真劈腿",
    "hot": 418632,
    "tag": "新",
    "link": "https://s.weibo.com/weibo?q=%E5%8D%8A%E7%86%9F%E7%94%B7%E5%A5%B3%20%E5%81%87%E7%A6%BB%E5%A9%9A%E7%9C%9F%E5%8A%88%E8%85%BF&t=31&band_rank=12&Refer=top"
  },
  {
    "rank": 13,
    "title": "青春还是太全面了",
    "hot": 390781,
    "tag": "新",
    "link": "https://s.weibo.com/weibo?q=%23%E9%9D%92%E6%98%A5%E8%BF%98%E6%98%AF%E5%A4%AA%E5%85%A8%E9%9D%A2%E4%BA%86%23&t=31&band_rank=13&Refer=top"
  },
  {
    "rank": 14,
    "title": "生命树",
    "hot": 390404,
    "tag": "新",
    "link": "https://s.weibo.com/weibo?q=%E7%94%9F%E5%91%BD%E6%A0%91&t=31&band_rank=14&Refer=top"
  },
  {
    "rank": 15,
    "title": "小区车位间距1.47米窄挪车需20分钟",
    "hot": 363307,
    "tag": "新",
    "link": "https://s.weibo.com/weibo?q=%23%E5%B0%8F%E5%8C%BA%E8%BD%A6%E4%BD%8D%E9%97%B4%E8%B7%9D1.47%E7%B1%B3%E7%AA%84%E6%8C%AA%E8%BD%A6%E9%9C%8020%E5%88%86%E9%92%9F%23&t=31&band_rank=15&Refer=top"
  },
  {
    "rank": 16,
    "title": "杨超越娱乐圈最好的朋友是黄明昊",
    "hot": 351404,
    "tag": "新",
    "link": "https://s.weibo.com/weibo?q=%E6%9D%A8%E8%B6%85%E8%B6%8A%E5%A8%B1%E4%B9%90%E5%9C%88%E6%9C%80%E5%A5%BD%E7%9A%84%E6%9C%8B%E5%8F%8B%E6%98%AF%E9%BB%84%E6%98%8E%E6%98%8A&t=31&band_rank=16&Refer=top"
  },
  {
    "rank": 17,
    "title": "老伴去世女子被继女要求搬离",
    "hot": 311044,
    "tag": "",
    "link": "https://s.weibo.com/weibo?q=%23%E8%80%81%E4%BC%B4%E5%8E%BB%E4%B8%96%E5%A5%B3%E5%AD%90%E8%A2%AB%E7%BB%A7%E5%A5%B3%E8%A6%81%E6%B1%82%E6%90%AC%E7%A6%BB%23&t=31&band_rank=17&Refer=top"
  },
  {
    "rank": 18,
    "title": "存量房贷利率调降呼声再起",
    "hot": 277942,
    "tag": "",
    "link": "https://s.weibo.com/weibo?q=%23%E5%AD%98%E9%87%8F%E6%88%BF%E8%B4%B7%E5%88%A9%E7%8E%87%E8%B0%83%E9%99%8D%E5%91%BC%E5%A3%B0%E5%86%8D%E8%B5%B7%23&t=31&band_rank=18&Refer=top"
  },
  {
    "rank": 19,
    "title": "美媒称以筹备通信设备爆炸至少15年",
    "hot": 246630,
    "tag": "",
    "link": "https://s.weibo.com/weibo?q=%23%E7%BE%8E%E5%AA%92%E7%A7%B0%E4%BB%A5%E7%AD%B9%E5%A4%87%E9%80%9A%E4%BF%A1%E8%AE%BE%E5%A4%87%E7%88%86%E7%82%B8%E8%87%B3%E5%B0%9115%E5%B9%B4%23&t=31&band_rank=19&Refer=top"
  },
  {
    "rank": 20,
    "title": "黄轩首次晒与女友视频",
    "hot": 246603,
    "tag": "新",
    "link": "https://s.weibo.com/weibo?q=%E9%BB%84%E8%BD%A9%E9%A6%96%E6%AC%A1%E6%99%92%E4%B8%8E%E5%A5%B3%E5%8F%8B%E8%A7%86%E9%A2%91&t=31&band_rank=20&Refer=top"
  },
  {
    "rank": 21,
    "title": "老叔拿离婚证骗小姑娘恋爱",
    "hot": 245607,
    "tag": "",
    "link": "https://s.weibo.com/weibo?q=%E8%80%81%E5%8F%94%E6%8B%BF%E7%A6%BB%E5%A9%9A%E8%AF%81%E9%AA%97%E5%B0%8F%E5%A7%91%E5%A8%98%E6%81%8B%E7%88%B1&t=31&band_rank=21&Refer=top"
  },
  {
    "rank": 22,
    "title": "蔡徐坤抱了赵露思的狗",
    "hot": 244778,
    "tag": "热",
    "link": "https://s.weibo.com/weibo?q=%23%E8%94%A1%E5%BE%90%E5%9D%A4%E6%8A%B1%E4%BA%86%E8%B5%B5%E9%9C%B2%E6%80%9D%E7%9A%84%E7%8B%97%23&t=31&band_rank=22&Refer=top"
  },
  {
    "rank": 23,
    "title": "网红良田正颌手术很成功",
    "hot": 243542,
    "tag": "新",
    "link": "https://s.weibo.com/weibo?q=%23%E7%BD%91%E7%BA%A2%E8%89%AF%E7%94%B0%E6%AD%A3%E9%A2%8C%E6%89%8B%E6%9C%AF%E5%BE%88%E6%88%90%E5%8A%9F%23&t=31&band_rank=23&Refer=top"
  },
  {
    "rank": 24,
    "title": "TOP登陆少年首次外务",
    "hot": 243202,
    "tag": "",
    "link": "https://s.weibo.com/weibo?q=%23TOP%E7%99%BB%E9%99%86%E5%B0%91%E5%B9%B4%E9%A6%96%E6%AC%A1%E5%A4%96%E5%8A%A1%23&t=31&band_rank=24&Refer=top"
  },
  {
    "rank": 25,
    "title": "台风普拉桑复活了",
    "hot": 242475,
    "tag": "新",
    "link": "https://s.weibo.com/weibo?q=%23%E5%8F%B0%E9%A3%8E%E6%99%AE%E6%8B%89%E6%A1%91%E5%A4%8D%E6%B4%BB%E4%BA%86%23&t=31&band_rank=25&Refer=top"
  },
  {
    "rank": 26,
    "title": "结婚后多少人敢空着手回娘家",
    "hot": 233021,
    "tag": "新",
    "link": "https://s.weibo.com/weibo?q=%23%E7%BB%93%E5%A9%9A%E5%90%8E%E5%A4%9A%E5%B0%91%E4%BA%BA%E6%95%A2%E7%A9%BA%E7%9D%80%E6%89%8B%E5%9B%9E%E5%A8%98%E5%AE%B6%23&t=31&band_rank=26&Refer=top"
  },
  {
    "rank": 27,
    "title": "iPhone17标准版或配120Hz高刷",
    "hot": 228250,
    "tag": "",
    "link": "https://s.weibo.com/weibo?q=%23iPhone17%E6%A0%87%E5%87%86%E7%89%88%E6%88%96%E9%85%8D120Hz%E9%AB%98%E5%88%B7%23&t=31&band_rank=27&Refer=top"
  },
  {
    "rank": 28,
    "title": "以色列曾给手机装炸药成功暗杀",
    "hot": 217076,
    "tag": "新",
    "link": "https://s.weibo.com/weibo?q=%23%E4%BB%A5%E8%89%B2%E5%88%97%E6%9B%BE%E7%BB%99%E6%89%8B%E6%9C%BA%E8%A3%85%E7%82%B8%E8%8D%AF%E6%88%90%E5%8A%9F%E6%9A%97%E6%9D%80%23&t=31&band_rank=28&Refer=top"
  },
  {
    "rank": 29,
    "title": "计算机二级 PPT",
    "hot": 213906,
    "tag": "新",
    "link": "https://s.weibo.com/weibo?q=%E8%AE%A1%E7%AE%97%E6%9C%BA%E4%BA%8C%E7%BA%A7%20PPT&t=31&band_rank=29&Refer=top"
  },
  {
    "rank": 30,
    "title": "王源发文为王俊凯庆生",
    "hot": 211017,
    "tag": "",
    "link": "https://s.weibo.com/weibo?q=%23%E7%8E%8B%E6%BA%90%E5%8F%91%E6%96%87%E4%B8%BA%E7%8E%8B%E4%BF%8A%E5%87%AF%E5%BA%86%E7%94%9F%23&t=31&band_rank=30&Refer=top"
  },
  {
    "rank": 31,
    "title": "杨紫 生命树",
    "hot": 206718,
    "tag": "新",
    "link": "https://s.weibo.com/weibo?q=%E6%9D%A8%E7%B4%AB%20%E7%94%9F%E5%91%BD%E6%A0%91&t=31&band_rank=31&Refer=top"
  },
  {
    "rank": 32,
    "title": "韩国诞生首例自然受孕5胞胎",
    "hot": 200322,
    "tag": "新",
    "link": "https://s.weibo.com/weibo?q=%23%E9%9F%A9%E5%9B%BD%E8%AF%9E%E7%94%9F%E9%A6%96%E4%BE%8B%E8%87%AA%E7%84%B6%E5%8F%97%E5%AD%955%E8%83%9E%E8%83%8E%23&t=31&band_rank=32&Refer=top"
  },
  {
    "rank": 33,
    "title": "尹锡悦发文感谢韩国夫妻生下5胞胎",
    "hot": 190862,
    "tag": "新",
    "link": "https://s.weibo.com/weibo?q=%23%E5%B0%B9%E9%94%A1%E6%82%A6%E5%8F%91%E6%96%87%E6%84%9F%E8%B0%A2%E9%9F%A9%E5%9B%BD%E5%A4%AB%E5%A6%BB%E7%94%9F%E4%B8%8B5%E8%83%9E%E8%83%8E%23&t=31&band_rank=33&Refer=top"
  },
  {
    "rank": 34,
    "title": "时代少年团李宁大秀",
    "hot": 185523,
    "tag": "新",
    "link": "https://s.weibo.com/weibo?q=%23%E6%97%B6%E4%BB%A3%E5%B0%91%E5%B9%B4%E5%9B%A2%E6%9D%8E%E5%AE%81%E5%A4%A7%E7%A7%80%23&t=31&band_rank=34&Refer=top"
  },
  {
    "rank": 35,
    "title": "男子凌晨4点散步失足坠海",
    "hot": 175593,
    "tag": "新",
    "link": "https://s.weibo.com/weibo?q=%23%E7%94%B7%E5%AD%90%E5%87%8C%E6%99%A84%E7%82%B9%E6%95%A3%E6%AD%A5%E5%A4%B1%E8%B6%B3%E5%9D%A0%E6%B5%B7%23&t=31&band_rank=35&Refer=top"
  },
  {
    "rank": 36,
    "title": "新疆葡萄干不是晒出来而是晾出来的",
    "hot": 162949,
    "tag": "新",
    "link": "https://s.weibo.com/weibo?q=%23%E6%96%B0%E7%96%86%E8%91%A1%E8%90%84%E5%B9%B2%E4%B8%8D%E6%98%AF%E6%99%92%E5%87%BA%E6%9D%A5%E8%80%8C%E6%98%AF%E6%99%BE%E5%87%BA%E6%9D%A5%E7%9A%84%23&t=31&band_rank=36&Refer=top"
  },
  {
    "rank": 37,
    "title": "为了live图把微信卸载聊天记录没了",
    "hot": 151060,
    "tag": "新",
    "link": "https://s.weibo.com/weibo?q=%23%E4%B8%BA%E4%BA%86live%E5%9B%BE%E6%8A%8A%E5%BE%AE%E4%BF%A1%E5%8D%B8%E8%BD%BD%E8%81%8A%E5%A4%A9%E8%AE%B0%E5%BD%95%E6%B2%A1%E4%BA%86%23&t=31&band_rank=37&Refer=top"
  },
  {
    "rank": 38,
    "title": "诺一霓娜最新采访",
    "hot": 149843,
    "tag": "新",
    "link": "https://s.weibo.com/weibo?q=%23%E8%AF%BA%E4%B8%80%E9%9C%93%E5%A8%9C%E6%9C%80%E6%96%B0%E9%87%87%E8%AE%BF%23&t=31&band_rank=38&Refer=top"
  },
  {
    "rank": 39,
    "title": "湾区升明月阵容",
    "hot": 145034,
    "tag": "",
    "link": "https://s.weibo.com/weibo?q=%23%E6%B9%BE%E5%8C%BA%E5%8D%87%E6%98%8E%E6%9C%88%E9%98%B5%E5%AE%B9%23&t=31&band_rank=39&Refer=top"
  },
  {
    "rank": 40,
    "title": "袁巴元维护张雨绮",
    "hot": 138888,
    "tag": "",
    "link": "https://s.weibo.com/weibo?q=%23%E8%A2%81%E5%B7%B4%E5%85%83%E7%BB%B4%E6%8A%A4%E5%BC%A0%E9%9B%A8%E7%BB%AE%23&t=31&band_rank=40&Refer=top"
  },
  {
    "rank": 41,
    "title": "孙千 程苗苗17岁的青春永不落幕",
    "hot": 134993,
    "tag": "",
    "link": "https://s.weibo.com/weibo?q=%E5%AD%99%E5%8D%83%20%E7%A8%8B%E8%8B%97%E8%8B%9717%E5%B2%81%E7%9A%84%E9%9D%92%E6%98%A5%E6%B0%B8%E4%B8%8D%E8%90%BD%E5%B9%95&t=31&band_rank=41&Refer=top"
  },
  {
    "rank": 42,
    "title": "文章马伊琍女儿16岁生日照",
    "hot": 127255,
    "tag": "",
    "link": "https://s.weibo.com/weibo?q=%23%E6%96%87%E7%AB%A0%E9%A9%AC%E4%BC%8A%E7%90%8D%E5%A5%B3%E5%84%BF16%E5%B2%81%E7%94%9F%E6%97%A5%E7%85%A7%23&t=31&band_rank=42&Refer=top"
  },
  {
    "rank": 43,
    "title": "这就是中国军人带来的安全感",
    "hot": 127007,
    "tag": "",
    "link": "https://s.weibo.com/weibo?q=%23%E8%BF%99%E5%B0%B1%E6%98%AF%E4%B8%AD%E5%9B%BD%E5%86%9B%E4%BA%BA%E5%B8%A6%E6%9D%A5%E7%9A%84%E5%AE%89%E5%85%A8%E6%84%9F%23&t=31&band_rank=43&Refer=top"
  },
  {
    "rank": 44,
    "title": "女生买模型被教官查房一眼发现",
    "hot": 121790,
    "tag": "新",
    "link": "https://s.weibo.com/weibo?q=%23%E5%A5%B3%E7%94%9F%E4%B9%B0%E6%A8%A1%E5%9E%8B%E8%A2%AB%E6%95%99%E5%AE%98%E6%9F%A5%E6%88%BF%E4%B8%80%E7%9C%BC%E5%8F%91%E7%8E%B0%23&t=31&band_rank=44&Refer=top"
  },
  {
    "rank": 45,
    "title": "赵露思登世趋",
    "hot": 121328,
    "tag": "",
    "link": "https://s.weibo.com/weibo?q=%23%E8%B5%B5%E9%9C%B2%E6%80%9D%E7%99%BB%E4%B8%96%E8%B6%8B%23&t=31&band_rank=45&Refer=top"
  },
  {
    "rank": 46,
    "title": "小狗狗嘬手手",
    "hot": 118169,
    "tag": "新",
    "link": "https://s.weibo.com/weibo?q=%E5%B0%8F%E7%8B%97%E7%8B%97%E5%98%AC%E6%89%8B%E6%89%8B&t=31&band_rank=46&Refer=top"
  },
  {
    "rank": 47,
    "title": "肖战湾区升明月有三首歌",
    "hot": 117784,
    "tag": "",
    "link": "https://s.weibo.com/weibo?q=%23%E8%82%96%E6%88%98%E6%B9%BE%E5%8C%BA%E5%8D%87%E6%98%8E%E6%9C%88%E6%9C%89%E4%B8%89%E9%A6%96%E6%AD%8C%23&t=31&band_rank=47&Refer=top"
  },
  {
    "rank": 48,
    "title": "黎巴嫩真主党曾为了安全才使用BP机",
    "hot": 117621,
    "tag": "",
    "link": "https://s.weibo.com/weibo?q=%23%E9%BB%8E%E5%B7%B4%E5%AB%A9%E7%9C%9F%E4%B8%BB%E5%85%9A%E6%9B%BE%E4%B8%BA%E4%BA%86%E5%AE%89%E5%85%A8%E6%89%8D%E4%BD%BF%E7%94%A8BP%E6%9C%BA%23&t=31&band_rank=48&Refer=top"
  },
  {
    "rank": 49,
    "title": "杨超越二搭丁禹兮演前任",
    "hot": 112992,
    "tag": "新",
    "link": "https://s.weibo.com/weibo?q=%E6%9D%A8%E8%B6%85%E8%B6%8A%E4%BA%8C%E6%90%AD%E4%B8%81%E7%A6%B9%E5%85%AE%E6%BC%94%E5%89%8D%E4%BB%BB&t=31&band_rank=49&Refer=top"
  },
  {
    "rank": 50,
    "title": "柏浪涛 刑法的神",
    "hot": 108261,
    "tag": "",
    "link": "https://s.weibo.com/weibo?q=%E6%9F%8F%E6%B5%AA%E6%B6%9B%20%E5%88%91%E6%B3%95%E7%9A%84%E7%A5%9E&t=31&band_rank=50&Refer=top"
  }
]
