[
  {
    "rank": 1,
    "title": "药王谷开诊1个多月15名患者死亡",
    "hot": 1657340,
    "tag": "新",
    "link": "https://s.weibo.com/weibo?q=%23%E8%8D%AF%E7%8E%8B%E8%B0%B7%E5%BC%80%E8%AF%8A1%E4%B8%AA%E5%A4%9A%E6%9C%8815%E5%90%8D%E6%82%A3%E8%80%85%E6%AD%BB%E4%BA%A1%23&t=31&band_rank=1&Refer=top"
  },
  {
    "rank": 2,
    "title": "黑白森林定档",
    "hot": 755759,
    "tag": "",
    "link": "https://s.weibo.com/weibo?q=%E9%BB%91%E7%99%BD%E6%A3%AE%E6%9E%97%E5%AE%9A%E6%A1%A3&t=31&band_rank=2&Refer=top"
  },
  {
    "rank": 3,
    "title": "南极中山国家大气本底监测站建成",
    "hot": 754017,
    "tag": "新",
    "link": "https://s.weibo.com/weibo?q=%23%E5%8D%97%E6%9E%81%E4%B8%AD%E5%B1%B1%E5%9B%BD%E5%AE%B6%E5%A4%A7%E6%B0%94%E6%9C%AC%E5%BA%95%E7%9B%91%E6%B5%8B%E7%AB%99%E5%BB%BA%E6%88%90%23&t=31&band_rank=3&Refer=top"
  },
  {
    "rank": 4,
    "title": "泰国坠崖孕妇11月直播14场",
    "hot": 753323,
    "tag": "",
    "link": "https://s.weibo.com/weibo?q=%23%E6%B3%B0%E5%9B%BD%E5%9D%A0%E5%B4%96%E5%AD%95%E5%A6%8711%E6%9C%88%E7%9B%B4%E6%92%AD14%E5%9C%BA%23&t=31&band_rank=4&Refer=top"
  },
  {
    "rank": 5,
    "title": "韩国流行周五下班去中国",
    "hot": 741148,
    "tag": "新",
    "link": "https://s.weibo.com/weibo?q=%23%E9%9F%A9%E5%9B%BD%E6%B5%81%E8%A1%8C%E5%91%A8%E4%BA%94%E4%B8%8B%E7%8F%AD%E5%8E%BB%E4%B8%AD%E5%9B%BD%23&t=31&band_rank=5&Refer=top"
  },
  {
    "rank": 6,
    "title": "骄阳似我官宣赵今麦宋威龙",
    "hot": 532184,
    "tag": "",
    "link": "https://s.weibo.com/weibo?q=%23%E9%AA%84%E9%98%B3%E4%BC%BC%E6%88%91%E5%AE%98%E5%AE%A3%E8%B5%B5%E4%BB%8A%E9%BA%A6%E5%AE%8B%E5%A8%81%E9%BE%99%23&t=31&band_rank=6&Refer=top"
  },
  {
    "rank": 7,
    "title": "金高银来杭州了",
    "hot": 524290,
    "tag": "新",
    "link": "https://s.weibo.com/weibo?q=%23%E9%87%91%E9%AB%98%E9%93%B6%E6%9D%A5%E6%9D%AD%E5%B7%9E%E4%BA%86%23&t=31&band_rank=7&Refer=top"
  },
  {
    "rank": 8,
    "title": "猎罪图鉴",
    "hot": 416827,
    "tag": "新",
    "link": "https://s.weibo.com/weibo?q=%E7%8C%8E%E7%BD%AA%E5%9B%BE%E9%89%B4&t=31&band_rank=8&Refer=top"
  },
  {
    "rank": 9,
    "title": "没想到吃剩的骨头还能这样用",
    "hot": 382255,
    "tag": "",
    "link": "https://s.weibo.com/weibo?q=%23%E6%B2%A1%E6%83%B3%E5%88%B0%E5%90%83%E5%89%A9%E7%9A%84%E9%AA%A8%E5%A4%B4%E8%BF%98%E8%83%BD%E8%BF%99%E6%A0%B7%E7%94%A8%23&t=31&band_rank=9&Refer=top"
  },
  {
    "rank": 10,
    "title": "川航回应3U8925航班备降桂林",
    "hot": 374569,
    "tag": "新",
    "link": "https://s.weibo.com/weibo?q=%23%E5%B7%9D%E8%88%AA%E5%9B%9E%E5%BA%943U8925%E8%88%AA%E7%8F%AD%E5%A4%87%E9%99%8D%E6%A1%82%E6%9E%97%23&t=31&band_rank=10&Refer=top"
  },
  {
    "rank": 11,
    "title": "姜云升谈陈近南diss周密",
    "hot": 372141,
    "tag": "新",
    "link": "https://s.weibo.com/weibo?q=%23%E5%A7%9C%E4%BA%91%E5%8D%87%E8%B0%88%E9%99%88%E8%BF%91%E5%8D%97diss%E5%91%A8%E5%AF%86%23&t=31&band_rank=11&Refer=top"
  },
  {
    "rank": 12,
    "title": "刘浩存掌管高马尾的神",
    "hot": 366175,
    "tag": "新",
    "link": "https://s.weibo.com/weibo?q=%E5%88%98%E6%B5%A9%E5%AD%98%E6%8E%8C%E7%AE%A1%E9%AB%98%E9%A9%AC%E5%B0%BE%E7%9A%84%E7%A5%9E&t=31&band_rank=12&Refer=top"
  },
  {
    "rank": 13,
    "title": "泰国坠崖孕妇被指责生意做太大",
    "hot": 352238,
    "tag": "热",
    "link": "https://s.weibo.com/weibo?q=%23%E6%B3%B0%E5%9B%BD%E5%9D%A0%E5%B4%96%E5%AD%95%E5%A6%87%E8%A2%AB%E6%8C%87%E8%B4%A3%E7%94%9F%E6%84%8F%E5%81%9A%E5%A4%AA%E5%A4%A7%23&t=31&band_rank=13&Refer=top"
  },
  {
    "rank": 14,
    "title": "腾讯12月大剧片单",
    "hot": 350355,
    "tag": "新",
    "link": "https://s.weibo.com/weibo?q=%23%E8%85%BE%E8%AE%AF12%E6%9C%88%E5%A4%A7%E5%89%A7%E7%89%87%E5%8D%95%23&t=31&band_rank=14&Refer=top"
  },
  {
    "rank": 15,
    "title": "今年乌军逃兵人数已超前两年之和",
    "hot": 347324,
    "tag": "新",
    "link": "https://s.weibo.com/weibo?q=%23%E4%BB%8A%E5%B9%B4%E4%B9%8C%E5%86%9B%E9%80%83%E5%85%B5%E4%BA%BA%E6%95%B0%E5%B7%B2%E8%B6%85%E5%89%8D%E4%B8%A4%E5%B9%B4%E4%B9%8B%E5%92%8C%23&t=31&band_rank=15&Refer=top"
  },
  {
    "rank": 16,
    "title": "李行亮12月至少有2个演出计划",
    "hot": 345147,
    "tag": "热",
    "link": "https://s.weibo.com/weibo?q=%23%E6%9D%8E%E8%A1%8C%E4%BA%AE12%E6%9C%88%E8%87%B3%E5%B0%91%E6%9C%892%E4%B8%AA%E6%BC%94%E5%87%BA%E8%AE%A1%E5%88%92%23&t=31&band_rank=16&Refer=top"
  },
  {
    "rank": 17,
    "title": "A股三大指数均涨逾1%",
    "hot": 337627,
    "tag": "新",
    "link": "https://s.weibo.com/weibo?q=%23A%E8%82%A1%E4%B8%89%E5%A4%A7%E6%8C%87%E6%95%B0%E5%9D%87%E6%B6%A8%E9%80%BE1%25%23&t=31&band_rank=17&Refer=top"
  },
  {
    "rank": 18,
    "title": "林诗栋蒯曼VS钱德拉瓦提克",
    "hot": 336256,
    "tag": "新",
    "link": "https://s.weibo.com/weibo?q=%23%E6%9E%97%E8%AF%97%E6%A0%8B%E8%92%AF%E6%9B%BCVS%E9%92%B1%E5%BE%B7%E6%8B%89%E7%93%A6%E6%8F%90%E5%85%8B%23&t=31&band_rank=18&Refer=top"
  },
  {
    "rank": 19,
    "title": "围观明星婚姻的观众成流量变现工具",
    "hot": 319048,
    "tag": "新",
    "link": "https://s.weibo.com/weibo?q=%23%E5%9B%B4%E8%A7%82%E6%98%8E%E6%98%9F%E5%A9%9A%E5%A7%BB%E7%9A%84%E8%A7%82%E4%BC%97%E6%88%90%E6%B5%81%E9%87%8F%E5%8F%98%E7%8E%B0%E5%B7%A5%E5%85%B7%23&t=31&band_rank=19&Refer=top"
  },
  {
    "rank": 20,
    "title": "泰国坠崖孕妇与管晨辰签约同家MCN",
    "hot": 309901,
    "tag": "新",
    "link": "https://s.weibo.com/weibo?q=%23%E6%B3%B0%E5%9B%BD%E5%9D%A0%E5%B4%96%E5%AD%95%E5%A6%87%E4%B8%8E%E7%AE%A1%E6%99%A8%E8%BE%B0%E7%AD%BE%E7%BA%A6%E5%90%8C%E5%AE%B6MCN%23&t=31&band_rank=20&Refer=top"
  },
  {
    "rank": 21,
    "title": "周芯竹 周密",
    "hot": 308403,
    "tag": "热",
    "link": "https://s.weibo.com/weibo?q=%E5%91%A8%E8%8A%AF%E7%AB%B9%20%E5%91%A8%E5%AF%86&t=31&band_rank=21&Refer=top"
  },
  {
    "rank": 22,
    "title": "红糖水没用 得吃去痛片",
    "hot": 292112,
    "tag": "新",
    "link": "https://s.weibo.com/weibo?q=%E7%BA%A2%E7%B3%96%E6%B0%B4%E6%B2%A1%E7%94%A8%20%E5%BE%97%E5%90%83%E5%8E%BB%E7%97%9B%E7%89%87&t=31&band_rank=22&Refer=top"
  },
  {
    "rank": 23,
    "title": "国乒vs印度",
    "hot": 291848,
    "tag": "新",
    "link": "https://s.weibo.com/weibo?q=%23%E5%9B%BD%E4%B9%92vs%E5%8D%B0%E5%BA%A6%23&t=31&band_rank=23&Refer=top"
  },
  {
    "rank": 24,
    "title": "冬日智驾追雪buff叠满",
    "hot": 291659,
    "tag": "",
    "link": "https://s.weibo.com/weibo?q=%23%E5%86%AC%E6%97%A5%E6%99%BA%E9%A9%BE%E8%BF%BD%E9%9B%AAbuff%E5%8F%A0%E6%BB%A1%23&t=31&band_rank=24&Refer=top"
  },
  {
    "rank": 25,
    "title": "iG官宣新阵容剪影",
    "hot": 291375,
    "tag": "新",
    "link": "https://s.weibo.com/weibo?q=%23iG%E5%AE%98%E5%AE%A3%E6%96%B0%E9%98%B5%E5%AE%B9%E5%89%AA%E5%BD%B1%23&t=31&band_rank=25&Refer=top"
  },
  {
    "rank": 26,
    "title": "周芯竹 高天佐",
    "hot": 290754,
    "tag": "",
    "link": "https://s.weibo.com/weibo?q=%E5%91%A8%E8%8A%AF%E7%AB%B9%20%E9%AB%98%E5%A4%A9%E4%BD%90&t=31&band_rank=26&Refer=top"
  },
  {
    "rank": 27,
    "title": "有些rapper不该把低俗当作风格",
    "hot": 290514,
    "tag": "",
    "link": "https://s.weibo.com/weibo?q=%23%E6%9C%89%E4%BA%9Brapper%E4%B8%8D%E8%AF%A5%E6%8A%8A%E4%BD%8E%E4%BF%97%E5%BD%93%E4%BD%9C%E9%A3%8E%E6%A0%BC%23&t=31&band_rank=27&Refer=top"
  },
  {
    "rank": 28,
    "title": "佟大为花期真长",
    "hot": 290105,
    "tag": "新",
    "link": "https://s.weibo.com/weibo?q=%E4%BD%9F%E5%A4%A7%E4%B8%BA%E8%8A%B1%E6%9C%9F%E7%9C%9F%E9%95%BF&t=31&band_rank=28&Refer=top"
  },
  {
    "rank": 29,
    "title": "香奈儿杭州全球首秀",
    "hot": 289678,
    "tag": "",
    "link": "https://s.weibo.com/weibo?q=%23%E9%A6%99%E5%A5%88%E5%84%BF%E6%9D%AD%E5%B7%9E%E5%85%A8%E7%90%83%E9%A6%96%E7%A7%80%23&t=31&band_rank=29&Refer=top"
  },
  {
    "rank": 30,
    "title": "综艺大赏",
    "hot": 288975,
    "tag": "新",
    "link": "https://s.weibo.com/weibo?q=%E7%BB%BC%E8%89%BA%E5%A4%A7%E8%B5%8F&t=31&band_rank=30&Refer=top"
  },
  {
    "rank": 31,
    "title": "堵车时闯绿灯属违法行为",
    "hot": 288597,
    "tag": "",
    "link": "https://s.weibo.com/weibo?q=%23%E5%A0%B5%E8%BD%A6%E6%97%B6%E9%97%AF%E7%BB%BF%E7%81%AF%E5%B1%9E%E8%BF%9D%E6%B3%95%E8%A1%8C%E4%B8%BA%23&t=31&band_rank=31&Refer=top"
  },
  {
    "rank": 32,
    "title": "赵丽颖女友视角报备日常",
    "hot": 288434,
    "tag": "新",
    "link": "https://s.weibo.com/weibo?q=%23%E8%B5%B5%E4%B8%BD%E9%A2%96%E5%A5%B3%E5%8F%8B%E8%A7%86%E8%A7%92%E6%8A%A5%E5%A4%87%E6%97%A5%E5%B8%B8%23&t=31&band_rank=32&Refer=top"
  },
  {
    "rank": 33,
    "title": "网友在小学废弃信箱发现多封投诉信",
    "hot": 288105,
    "tag": "新",
    "link": "https://s.weibo.com/weibo?q=%23%E7%BD%91%E5%8F%8B%E5%9C%A8%E5%B0%8F%E5%AD%A6%E5%BA%9F%E5%BC%83%E4%BF%A1%E7%AE%B1%E5%8F%91%E7%8E%B0%E5%A4%9A%E5%B0%81%E6%8A%95%E8%AF%89%E4%BF%A1%23&t=31&band_rank=33&Refer=top"
  },
  {
    "rank": 34,
    "title": "单霁翔为保护故宫地面坚持穿布鞋",
    "hot": 261708,
    "tag": "",
    "link": "https://s.weibo.com/weibo?q=%23%E5%8D%95%E9%9C%81%E7%BF%94%E4%B8%BA%E4%BF%9D%E6%8A%A4%E6%95%85%E5%AE%AB%E5%9C%B0%E9%9D%A2%E5%9D%9A%E6%8C%81%E7%A9%BF%E5%B8%83%E9%9E%8B%23&t=31&band_rank=34&Refer=top"
  },
  {
    "rank": 35,
    "title": "丁禹兮今年第四部剧",
    "hot": 257366,
    "tag": "新",
    "link": "https://s.weibo.com/weibo?q=%23%E4%B8%81%E7%A6%B9%E5%85%AE%E4%BB%8A%E5%B9%B4%E7%AC%AC%E5%9B%9B%E9%83%A8%E5%89%A7%23&t=31&band_rank=35&Refer=top"
  },
  {
    "rank": 36,
    "title": "胃病变胃癌前一般有5个症状",
    "hot": 256067,
    "tag": "",
    "link": "https://s.weibo.com/weibo?q=%23%E8%83%83%E7%97%85%E5%8F%98%E8%83%83%E7%99%8C%E5%89%8D%E4%B8%80%E8%88%AC%E6%9C%895%E4%B8%AA%E7%97%87%E7%8A%B6%23&t=31&band_rank=36&Refer=top"
  },
  {
    "rank": 37,
    "title": "90后女护士将房间住包浆后失联",
    "hot": 254273,
    "tag": "",
    "link": "https://s.weibo.com/weibo?q=%2390%E5%90%8E%E5%A5%B3%E6%8A%A4%E5%A3%AB%E5%B0%86%E6%88%BF%E9%97%B4%E4%BD%8F%E5%8C%85%E6%B5%86%E5%90%8E%E5%A4%B1%E8%81%94%23&t=31&band_rank=37&Refer=top"
  },
  {
    "rank": 38,
    "title": "iG新阵容将在传奇杯决赛现场公布",
    "hot": 246969,
    "tag": "新",
    "link": "https://s.weibo.com/weibo?q=%23iG%E6%96%B0%E9%98%B5%E5%AE%B9%E5%B0%86%E5%9C%A8%E4%BC%A0%E5%A5%87%E6%9D%AF%E5%86%B3%E8%B5%9B%E7%8E%B0%E5%9C%BA%E5%85%AC%E5%B8%83%23&t=31&band_rank=38&Refer=top"
  },
  {
    "rank": 39,
    "title": "川航一航班因旅客充电宝冒烟备降",
    "hot": 233465,
    "tag": "新",
    "link": "https://s.weibo.com/weibo?q=%23%E5%B7%9D%E8%88%AA%E4%B8%80%E8%88%AA%E7%8F%AD%E5%9B%A0%E6%97%85%E5%AE%A2%E5%85%85%E7%94%B5%E5%AE%9D%E5%86%92%E7%83%9F%E5%A4%87%E9%99%8D%23&t=31&band_rank=39&Refer=top"
  },
  {
    "rank": 40,
    "title": "摇光录",
    "hot": 228064,
    "tag": "新",
    "link": "https://s.weibo.com/weibo?q=%E6%91%87%E5%85%89%E5%BD%95&t=31&band_rank=40&Refer=top"
  },
  {
    "rank": 41,
    "title": "九重紫定档",
    "hot": 216614,
    "tag": "",
    "link": "https://s.weibo.com/weibo?q=%E4%B9%9D%E9%87%8D%E7%B4%AB%E5%AE%9A%E6%A1%A3&t=31&band_rank=41&Refer=top"
  },
  {
    "rank": 42,
    "title": "因穷写网文写成茅盾奖",
    "hot": 214116,
    "tag": "新",
    "link": "https://s.weibo.com/weibo?q=%23%E5%9B%A0%E7%A9%B7%E5%86%99%E7%BD%91%E6%96%87%E5%86%99%E6%88%90%E8%8C%85%E7%9B%BE%E5%A5%96%23&t=31&band_rank=42&Refer=top"
  },
  {
    "rank": 43,
    "title": "孟子义首演重生复仇大女主",
    "hot": 205476,
    "tag": "新",
    "link": "https://s.weibo.com/weibo?q=%E5%AD%9F%E5%AD%90%E4%B9%89%E9%A6%96%E6%BC%94%E9%87%8D%E7%94%9F%E5%A4%8D%E4%BB%87%E5%A4%A7%E5%A5%B3%E4%B8%BB&t=31&band_rank=43&Refer=top"
  },
  {
    "rank": 44,
    "title": "陈都灵月鳞绮纪出妆路透",
    "hot": 197256,
    "tag": "新",
    "link": "https://s.weibo.com/weibo?q=%23%E9%99%88%E9%83%BD%E7%81%B5%E6%9C%88%E9%B3%9E%E7%BB%AE%E7%BA%AA%E5%87%BA%E5%A6%86%E8%B7%AF%E9%80%8F%23&t=31&band_rank=44&Refer=top"
  },
  {
    "rank": 45,
    "title": "高钧贤结婚当爸",
    "hot": 196175,
    "tag": "新",
    "link": "https://s.weibo.com/weibo?q=%23%E9%AB%98%E9%92%A7%E8%B4%A4%E7%BB%93%E5%A9%9A%E5%BD%93%E7%88%B8%23&t=31&band_rank=45&Refer=top"
  },
  {
    "rank": 46,
    "title": "学信网发了永夜星河",
    "hot": 195335,
    "tag": "",
    "link": "https://s.weibo.com/weibo?q=%23%E5%AD%A6%E4%BF%A1%E7%BD%91%E5%8F%91%E4%BA%86%E6%B0%B8%E5%A4%9C%E6%98%9F%E6%B2%B3%23&t=31&band_rank=46&Refer=top"
  },
  {
    "rank": 47,
    "title": "aespa 星际女战士winter",
    "hot": 187647,
    "tag": "新",
    "link": "https://s.weibo.com/weibo?q=aespa%20%E6%98%9F%E9%99%85%E5%A5%B3%E6%88%98%E5%A3%ABwinter&t=31&band_rank=47&Refer=top"
  },
  {
    "rank": 48,
    "title": "4种体质的女性易患多囊",
    "hot": 187531,
    "tag": "新",
    "link": "https://s.weibo.com/weibo?q=%234%E7%A7%8D%E4%BD%93%E8%B4%A8%E7%9A%84%E5%A5%B3%E6%80%A7%E6%98%93%E6%82%A3%E5%A4%9A%E5%9B%8A%23&t=31&band_rank=48&Refer=top"
  },
  {
    "rank": 49,
    "title": "丞磊助理",
    "hot": 181846,
    "tag": "新",
    "link": "https://s.weibo.com/weibo?q=%23%E4%B8%9E%E7%A3%8A%E5%8A%A9%E7%90%86%23&t=31&band_rank=49&Refer=top"
  },
  {
    "rank": 50,
    "title": "安室透知道柯南身份",
    "hot": 175888,
    "tag": "",
    "link": "https://s.weibo.com/weibo?q=%E5%AE%89%E5%AE%A4%E9%80%8F%E7%9F%A5%E9%81%93%E6%9F%AF%E5%8D%97%E8%BA%AB%E4%BB%BD&t=31&band_rank=50&Refer=top"
  }
]
