[
  {
    "rank": 1,
    "title": "内娱唯一说微调结果没人信的人",
    "hot": 1233682,
    "tag": "新",
    "link": "https://s.weibo.com/weibo?q=%E5%86%85%E5%A8%B1%E5%94%AF%E4%B8%80%E8%AF%B4%E5%BE%AE%E8%B0%83%E7%BB%93%E6%9E%9C%E6%B2%A1%E4%BA%BA%E4%BF%A1%E7%9A%84%E4%BA%BA&t=31&band_rank=1&Refer=top"
  },
  {
    "rank": 2,
    "title": "公务员为离职故意旷工触发辞退条款",
    "hot": 859882,
    "tag": "热",
    "link": "https://s.weibo.com/weibo?q=%23%E5%85%AC%E5%8A%A1%E5%91%98%E4%B8%BA%E7%A6%BB%E8%81%8C%E6%95%85%E6%84%8F%E6%97%B7%E5%B7%A5%E8%A7%A6%E5%8F%91%E8%BE%9E%E9%80%80%E6%9D%A1%E6%AC%BE%23&t=31&band_rank=2&Refer=top"
  },
  {
    "rank": 3,
    "title": "2月起一批新规将施行",
    "hot": 715306,
    "tag": "",
    "link": "https://s.weibo.com/weibo?q=%232%E6%9C%88%E8%B5%B7%E4%B8%80%E6%89%B9%E6%96%B0%E8%A7%84%E5%B0%86%E6%96%BD%E8%A1%8C%23&t=31&band_rank=3&Refer=top"
  },
  {
    "rank": 4,
    "title": "生命树收视率",
    "hot": 614971,
    "tag": "新",
    "link": "https://s.weibo.com/weibo?q=%E7%94%9F%E5%91%BD%E6%A0%91%E6%94%B6%E8%A7%86%E7%8E%87&t=31&band_rank=4&Refer=top"
  },
  {
    "rank": 5,
    "title": "全球抛售美国",
    "hot": 498084,
    "tag": "新",
    "link": "https://s.weibo.com/weibo?q=%23%E5%85%A8%E7%90%83%E6%8A%9B%E5%94%AE%E7%BE%8E%E5%9B%BD%23&t=31&band_rank=5&Refer=top"
  },
  {
    "rank": 6,
    "title": "伊朗",
    "hot": 485065,
    "tag": "新",
    "link": "https://s.weibo.com/weibo?q=%E4%BC%8A%E6%9C%97&t=31&band_rank=6&Refer=top"
  },
  {
    "rank": 7,
    "title": "发明洗澡吃橙子的人是个天才",
    "hot": 338574,
    "tag": "",
    "link": "https://s.weibo.com/weibo?q=%E5%8F%91%E6%98%8E%E6%B4%97%E6%BE%A1%E5%90%83%E6%A9%99%E5%AD%90%E7%9A%84%E4%BA%BA%E6%98%AF%E4%B8%AA%E5%A4%A9%E6%89%8D&t=31&band_rank=7&Refer=top"
  },
  {
    "rank": 8,
    "title": "生命树",
    "hot": 323042,
    "tag": "沸",
    "link": "https://s.weibo.com/weibo?q=%E7%94%9F%E5%91%BD%E6%A0%91&t=31&band_rank=8&Refer=top"
  },
  {
    "rank": 9,
    "title": "已有4000家绝味鸭脖倒下",
    "hot": 290932,
    "tag": "新",
    "link": "https://s.weibo.com/weibo?q=%23%E5%B7%B2%E6%9C%894000%E5%AE%B6%E7%BB%9D%E5%91%B3%E9%B8%AD%E8%84%96%E5%80%92%E4%B8%8B%23&t=31&band_rank=9&Refer=top"
  },
  {
    "rank": 10,
    "title": "名侦探柯南 联动",
    "hot": 273835,
    "tag": "",
    "link": "https://s.weibo.com/weibo?q=%E5%90%8D%E4%BE%A6%E6%8E%A2%E6%9F%AF%E5%8D%97%20%E8%81%94%E5%8A%A8&t=31&band_rank=10&Refer=top"
  },
  {
    "rank": 11,
    "title": "一栗小莎子回应确诊淋巴瘤",
    "hot": 266343,
    "tag": "",
    "link": "https://s.weibo.com/weibo?q=%23%E4%B8%80%E6%A0%97%E5%B0%8F%E8%8E%8E%E5%AD%90%E5%9B%9E%E5%BA%94%E7%A1%AE%E8%AF%8A%E6%B7%8B%E5%B7%B4%E7%98%A4%23&t=31&band_rank=11&Refer=top"
  },
  {
    "rank": 12,
    "title": "家委会收每生263元家长报警",
    "hot": 260293,
    "tag": "",
    "link": "https://s.weibo.com/weibo?q=%23%E5%AE%B6%E5%A7%94%E4%BC%9A%E6%94%B6%E6%AF%8F%E7%94%9F263%E5%85%83%E5%AE%B6%E9%95%BF%E6%8A%A5%E8%AD%A6%23&t=31&band_rank=12&Refer=top"
  },
  {
    "rank": 13,
    "title": "TF四代赢了TOP",
    "hot": 250144,
    "tag": "",
    "link": "https://s.weibo.com/weibo?q=%23TF%E5%9B%9B%E4%BB%A3%E8%B5%A2%E4%BA%86TOP%23&t=31&band_rank=13&Refer=top"
  },
  {
    "rank": 14,
    "title": "在飞机上删了五个小时的照片",
    "hot": 239428,
    "tag": "热",
    "link": "https://s.weibo.com/weibo?q=%E5%9C%A8%E9%A3%9E%E6%9C%BA%E4%B8%8A%E5%88%A0%E4%BA%86%E4%BA%94%E4%B8%AA%E5%B0%8F%E6%97%B6%E7%9A%84%E7%85%A7%E7%89%87&t=31&band_rank=14&Refer=top"
  },
  {
    "rank": 15,
    "title": "王一博 春晚",
    "hot": 238347,
    "tag": "",
    "link": "https://s.weibo.com/weibo?q=%E7%8E%8B%E4%B8%80%E5%8D%9A%20%E6%98%A5%E6%99%9A&t=31&band_rank=15&Refer=top"
  },
  {
    "rank": 16,
    "title": "黄金白银创单日暴跌纪录",
    "hot": 235680,
    "tag": "",
    "link": "https://s.weibo.com/weibo?q=%23%E9%BB%84%E9%87%91%E7%99%BD%E9%93%B6%E5%88%9B%E5%8D%95%E6%97%A5%E6%9A%B4%E8%B7%8C%E7%BA%AA%E5%BD%95%23&t=31&band_rank=16&Refer=top"
  },
  {
    "rank": 17,
    "title": "金价波动",
    "hot": 232710,
    "tag": "新",
    "link": "https://s.weibo.com/weibo?q=%E9%87%91%E4%BB%B7%E6%B3%A2%E5%8A%A8&t=31&band_rank=17&Refer=top"
  },
  {
    "rank": 18,
    "title": "宁艺卓合作舞台呢",
    "hot": 205349,
    "tag": "新",
    "link": "https://s.weibo.com/weibo?q=%E5%AE%81%E8%89%BA%E5%8D%93%E5%90%88%E4%BD%9C%E8%88%9E%E5%8F%B0%E5%91%A2&t=31&band_rank=18&Refer=top"
  },
  {
    "rank": 19,
    "title": "朴信惠母亲自曝不愿看天国的阶梯",
    "hot": 198130,
    "tag": "",
    "link": "https://s.weibo.com/weibo?q=%23%E6%9C%B4%E4%BF%A1%E6%83%A0%E6%AF%8D%E4%BA%B2%E8%87%AA%E6%9B%9D%E4%B8%8D%E6%84%BF%E7%9C%8B%E5%A4%A9%E5%9B%BD%E7%9A%84%E9%98%B6%E6%A2%AF%23&t=31&band_rank=19&Refer=top"
  },
  {
    "rank": 20,
    "title": "GuanG发博",
    "hot": 167673,
    "tag": "",
    "link": "https://s.weibo.com/weibo?q=GuanG%E5%8F%91%E5%8D%9A&t=31&band_rank=20&Refer=top"
  },
  {
    "rank": 21,
    "title": "我和金瀚何曾有过嫌隙",
    "hot": 167589,
    "tag": "新",
    "link": "https://s.weibo.com/weibo?q=%E6%88%91%E5%92%8C%E9%87%91%E7%80%9A%E4%BD%95%E6%9B%BE%E6%9C%89%E8%BF%87%E5%AB%8C%E9%9A%99&t=31&band_rank=21&Refer=top"
  },
  {
    "rank": 22,
    "title": "低丸子头是穿羽绒服最好看的发型",
    "hot": 167096,
    "tag": "",
    "link": "https://s.weibo.com/weibo?q=%E4%BD%8E%E4%B8%B8%E5%AD%90%E5%A4%B4%E6%98%AF%E7%A9%BF%E7%BE%BD%E7%BB%92%E6%9C%8D%E6%9C%80%E5%A5%BD%E7%9C%8B%E7%9A%84%E5%8F%91%E5%9E%8B&t=31&band_rank=22&Refer=top"
  },
  {
    "rank": 23,
    "title": "王橹杰跪地凝视",
    "hot": 166619,
    "tag": "",
    "link": "https://s.weibo.com/weibo?q=%23%E7%8E%8B%E6%A9%B9%E6%9D%B0%E8%B7%AA%E5%9C%B0%E5%87%9D%E8%A7%86%23&t=31&band_rank=23&Refer=top"
  },
  {
    "rank": 24,
    "title": "生命树 正午阳光",
    "hot": 166005,
    "tag": "新",
    "link": "https://s.weibo.com/weibo?q=%E7%94%9F%E5%91%BD%E6%A0%91%20%E6%AD%A3%E5%8D%88%E9%98%B3%E5%85%89&t=31&band_rank=24&Refer=top"
  },
  {
    "rank": 25,
    "title": "伊朗阿巴斯港一栋居民楼传出爆炸声",
    "hot": 162378,
    "tag": "新",
    "link": "https://s.weibo.com/weibo?q=%23%E4%BC%8A%E6%9C%97%E9%98%BF%E5%B7%B4%E6%96%AF%E6%B8%AF%E4%B8%80%E6%A0%8B%E5%B1%85%E6%B0%91%E6%A5%BC%E4%BC%A0%E5%87%BA%E7%88%86%E7%82%B8%E5%A3%B0%23&t=31&band_rank=25&Refer=top"
  },
  {
    "rank": 26,
    "title": "董璇晒朵朵出生照",
    "hot": 160287,
    "tag": "新",
    "link": "https://s.weibo.com/weibo?q=%23%E8%91%A3%E7%92%87%E6%99%92%E6%9C%B5%E6%9C%B5%E5%87%BA%E7%94%9F%E7%85%A7%23&t=31&band_rank=26&Refer=top"
  },
  {
    "rank": 27,
    "title": "原来能让王一博回归内娱的是央妈",
    "hot": 158127,
    "tag": "新",
    "link": "https://s.weibo.com/weibo?q=%23%E5%8E%9F%E6%9D%A5%E8%83%BD%E8%AE%A9%E7%8E%8B%E4%B8%80%E5%8D%9A%E5%9B%9E%E5%BD%92%E5%86%85%E5%A8%B1%E7%9A%84%E6%98%AF%E5%A4%AE%E5%A6%88%23&t=31&band_rank=27&Refer=top"
  },
  {
    "rank": 28,
    "title": "高中生熬夜用小太阳取暖突发脑梗",
    "hot": 157604,
    "tag": "新",
    "link": "https://s.weibo.com/weibo?q=%23%E9%AB%98%E4%B8%AD%E7%94%9F%E7%86%AC%E5%A4%9C%E7%94%A8%E5%B0%8F%E5%A4%AA%E9%98%B3%E5%8F%96%E6%9A%96%E7%AA%81%E5%8F%91%E8%84%91%E6%A2%97%23&t=31&band_rank=28&Refer=top"
  },
  {
    "rank": 29,
    "title": "张杰真让月亮爬上来了",
    "hot": 157139,
    "tag": "新",
    "link": "https://s.weibo.com/weibo?q=%23%E5%BC%A0%E6%9D%B0%E7%9C%9F%E8%AE%A9%E6%9C%88%E4%BA%AE%E7%88%AC%E4%B8%8A%E6%9D%A5%E4%BA%86%23&t=31&band_rank=29&Refer=top"
  },
  {
    "rank": 30,
    "title": "ZOO舞台",
    "hot": 145950,
    "tag": "",
    "link": "https://s.weibo.com/weibo?q=ZOO%E8%88%9E%E5%8F%B0&t=31&band_rank=30&Refer=top"
  },
  {
    "rank": 31,
    "title": "妈妈回应请1米86儿子当模特走红",
    "hot": 142382,
    "tag": "",
    "link": "https://s.weibo.com/weibo?q=%23%E5%A6%88%E5%A6%88%E5%9B%9E%E5%BA%94%E8%AF%B71%E7%B1%B386%E5%84%BF%E5%AD%90%E5%BD%93%E6%A8%A1%E7%89%B9%E8%B5%B0%E7%BA%A2%23&t=31&band_rank=31&Refer=top"
  },
  {
    "rank": 32,
    "title": "酷云",
    "hot": 141763,
    "tag": "新",
    "link": "https://s.weibo.com/weibo?q=%E9%85%B7%E4%BA%91&t=31&band_rank=32&Refer=top"
  },
  {
    "rank": 33,
    "title": "冯提莫自曝雄性激素过多",
    "hot": 138287,
    "tag": "新",
    "link": "https://s.weibo.com/weibo?q=%23%E5%86%AF%E6%8F%90%E8%8E%AB%E8%87%AA%E6%9B%9D%E9%9B%84%E6%80%A7%E6%BF%80%E7%B4%A0%E8%BF%87%E5%A4%9A%23&t=31&band_rank=33&Refer=top"
  },
  {
    "rank": 34,
    "title": "黄金创40年来最大单日跌幅",
    "hot": 117844,
    "tag": "新",
    "link": "https://s.weibo.com/weibo?q=%23%E9%BB%84%E9%87%91%E5%88%9B40%E5%B9%B4%E6%9D%A5%E6%9C%80%E5%A4%A7%E5%8D%95%E6%97%A5%E8%B7%8C%E5%B9%85%23&t=31&band_rank=34&Refer=top"
  },
  {
    "rank": 35,
    "title": "朱志鑫苏新皓毕竟回到澳门了",
    "hot": 113332,
    "tag": "",
    "link": "https://s.weibo.com/weibo?q=%23%E6%9C%B1%E5%BF%97%E9%91%AB%E8%8B%8F%E6%96%B0%E7%9A%93%E6%AF%95%E7%AB%9F%E5%9B%9E%E5%88%B0%E6%BE%B3%E9%97%A8%E4%BA%86%23&t=31&band_rank=35&Refer=top"
  },
  {
    "rank": 36,
    "title": "莱巴金娜夺冠",
    "hot": 105842,
    "tag": "",
    "link": "https://s.weibo.com/weibo?q=%E8%8E%B1%E5%B7%B4%E9%87%91%E5%A8%9C%E5%A4%BA%E5%86%A0&t=31&band_rank=36&Refer=top"
  },
  {
    "rank": 37,
    "title": "CBA",
    "hot": 104884,
    "tag": "新",
    "link": "https://s.weibo.com/weibo?q=CBA&t=31&band_rank=37&Refer=top"
  },
  {
    "rank": 38,
    "title": "英国首相一行吃光牛肝菌焖饭",
    "hot": 97487,
    "tag": "",
    "link": "https://s.weibo.com/weibo?q=%23%E8%8B%B1%E5%9B%BD%E9%A6%96%E7%9B%B8%E4%B8%80%E8%A1%8C%E5%90%83%E5%85%89%E7%89%9B%E8%82%9D%E8%8F%8C%E7%84%96%E9%A5%AD%23&t=31&band_rank=38&Refer=top"
  },
  {
    "rank": 39,
    "title": "春晚三彩老中青三代齐了",
    "hot": 95893,
    "tag": "新",
    "link": "https://s.weibo.com/weibo?q=%23%E6%98%A5%E6%99%9A%E4%B8%89%E5%BD%A9%E8%80%81%E4%B8%AD%E9%9D%92%E4%B8%89%E4%BB%A3%E9%BD%90%E4%BA%86%23&t=31&band_rank=39&Refer=top"
  },
  {
    "rank": 40,
    "title": "等一小时外卖结果发现自己根本没支付",
    "hot": 95839,
    "tag": "新",
    "link": "https://s.weibo.com/weibo?q=%E7%AD%89%E4%B8%80%E5%B0%8F%E6%97%B6%E5%A4%96%E5%8D%96%E7%BB%93%E6%9E%9C%E5%8F%91%E7%8E%B0%E8%87%AA%E5%B7%B1%E6%A0%B9%E6%9C%AC%E6%B2%A1%E6%94%AF%E4%BB%98&t=31&band_rank=40&Refer=top"
  },
  {
    "rank": 41,
    "title": "疑似十日终焉剪辑师泄露剧本",
    "hot": 95825,
    "tag": "新",
    "link": "https://s.weibo.com/weibo?q=%23%E7%96%91%E4%BC%BC%E5%8D%81%E6%97%A5%E7%BB%88%E7%84%89%E5%89%AA%E8%BE%91%E5%B8%88%E6%B3%84%E9%9C%B2%E5%89%A7%E6%9C%AC%23&t=31&band_rank=41&Refer=top"
  },
  {
    "rank": 42,
    "title": "微博之夜",
    "hot": 95570,
    "tag": "新",
    "link": "https://s.weibo.com/weibo?q=%E5%BE%AE%E5%8D%9A%E4%B9%8B%E5%A4%9C&t=31&band_rank=42&Refer=top"
  },
  {
    "rank": 43,
    "title": "BLG对战iG",
    "hot": 95286,
    "tag": "新",
    "link": "https://s.weibo.com/weibo?q=%23BLG%E5%AF%B9%E6%88%98iG%23&t=31&band_rank=43&Refer=top"
  },
  {
    "rank": 44,
    "title": "生命树第二集发生了什么",
    "hot": 94995,
    "tag": "新",
    "link": "https://s.weibo.com/weibo?q=%23%E7%94%9F%E5%91%BD%E6%A0%91%E7%AC%AC%E4%BA%8C%E9%9B%86%E5%8F%91%E7%94%9F%E4%BA%86%E4%BB%80%E4%B9%88%23&t=31&band_rank=44&Refer=top"
  },
  {
    "rank": 45,
    "title": "侯明昊直播",
    "hot": 94166,
    "tag": "新",
    "link": "https://s.weibo.com/weibo?q=%23%E4%BE%AF%E6%98%8E%E6%98%8A%E7%9B%B4%E6%92%AD%23&t=31&band_rank=45&Refer=top"
  },
  {
    "rank": 46,
    "title": "国内金饰克价一夜跌140元",
    "hot": 92661,
    "tag": "",
    "link": "https://s.weibo.com/weibo?q=%E5%9B%BD%E5%86%85%E9%87%91%E9%A5%B0%E5%85%8B%E4%BB%B7%E4%B8%80%E5%A4%9C%E8%B7%8C140%E5%85%83&t=31&band_rank=46&Refer=top"
  },
  {
    "rank": 47,
    "title": "突然的喜欢大结局",
    "hot": 92417,
    "tag": "新",
    "link": "https://s.weibo.com/weibo?q=%E7%AA%81%E7%84%B6%E7%9A%84%E5%96%9C%E6%AC%A2%E5%A4%A7%E7%BB%93%E5%B1%80&t=31&band_rank=47&Refer=top"
  },
  {
    "rank": 48,
    "title": "荣耀之战排名",
    "hot": 91045,
    "tag": "",
    "link": "https://s.weibo.com/weibo?q=%23%E8%8D%A3%E8%80%80%E4%B9%8B%E6%88%98%E6%8E%92%E5%90%8D%23&t=31&band_rank=48&Refer=top"
  },
  {
    "rank": 49,
    "title": "伊媒否认革命卫队海军司令遭暗杀传闻",
    "hot": 89903,
    "tag": "新",
    "link": "https://s.weibo.com/weibo?q=%23%E4%BC%8A%E5%AA%92%E5%90%A6%E8%AE%A4%E9%9D%A9%E5%91%BD%E5%8D%AB%E9%98%9F%E6%B5%B7%E5%86%9B%E5%8F%B8%E4%BB%A4%E9%81%AD%E6%9A%97%E6%9D%80%E4%BC%A0%E9%97%BB%23&t=31&band_rank=49&Refer=top"
  },
  {
    "rank": 50,
    "title": "HLE与GEN生死战",
    "hot": 89176,
    "tag": "新",
    "link": "https://s.weibo.com/weibo?q=%23HLE%E4%B8%8EGEN%E7%94%9F%E6%AD%BB%E6%88%98%23&t=31&band_rank=50&Refer=top"
  }
]
